tlctl/__debug__.py
tlctl/__init__.py
tlctl-2022.6.20.dist-info/LICENSE
tlctl-2022.6.20.dist-info/METADATA
tlctl-2022.6.20.dist-info/WHEEL
tlctl-2022.6.20.dist-info/top_level.txt
tlctl-2022.6.20.dist-info/RECORD
