Metadata-Version: 2.1
Name: tlctl
Version: 2022.6.20
Summary: tlctl
Home-page: https://github.com/atpuxiner/tlctl
Author: axiner
Author-email: atpuxiner@163.com
License: MIT
Platform: any
Classifier: License :: OSI Approved :: MIT License
Classifier: Operating System :: OS Independent
Classifier: Programming Language :: Python :: 3
Requires-Python: >=3.7
License-File: LICENSE
